mixture_of_attention/__init__.py
mixture_of_attention/attend.py
mixture_of_attention/autoregressive_wrapper.py
mixture_of_attention/mixture_of_attention.py
mixture_of_attention/rotary_emb.py
mixture_of_attention/transformer.py
mixture_of_attention-0.0.25.dist-info/LICENSE
mixture_of_attention-0.0.25.dist-info/METADATA
mixture_of_attention-0.0.25.dist-info/WHEEL
mixture_of_attention-0.0.25.dist-info/top_level.txt
mixture_of_attention-0.0.25.dist-info/RECORD
