Metadata-Version: 2.1
Name: mixture-of-attention
Version: 0.0.25
Summary: Mixture of Attention
Home-page: https://github.com/lucidrains/mixture-of-attention
Author: Phil Wang
Author-email: lucidrains@gmail.com
License: MIT
Keywords: artificial intelligence,deep learning,transformers,attention mechanism,mixture-of-experts,routed attention
Classifier: Development Status :: 4 - Beta
Classifier: Intended Audience :: Developers
Classifier: Topic :: Scientific/Engineering :: Artificial Intelligence
Classifier: License :: OSI Approved :: MIT License
Classifier: Programming Language :: Python :: 3.6
License-File: LICENSE
Requires-Dist: colt5-attention >=0.10.14
Requires-Dist: einops >=0.6.1
Requires-Dist: local-attention >=1.8.6
Requires-Dist: torch >=1.6
